smoothquant/__init__.py
smoothquant-0.0.1.dev0.dist-info/METADATA
smoothquant-0.0.1.dev0.dist-info/WHEEL
smoothquant-0.0.1.dev0.dist-info/top_level.txt
smoothquant-0.0.1.dev0.dist-info/RECORD
