Metadata-Version: 2.1
Name: smoothquant
Version: 0.0.1.dev0
Summary: SmoothQuant: Accurate and Efficient Post-Training Quantization for Large Language Models
Author: Shadow Walker
License: UNKNOWN
Keywords: smoothquant
Platform: UNKNOWN
Classifier: Programming Language :: Python :: 3
Classifier: Programming Language :: Python :: 3.8
Classifier: Programming Language :: Python :: 3.9
Classifier: Programming Language :: Python :: 3.10
Requires-Dist: torch
